Workbook
Name D: WACC!$D$15
Name D_perc: WACC!$D$17
Name E: WACC!$D$14
Name E_perc: WACC!$D$16
Name kd: WACC!$D$19
Name ke: WACC!$D$12
Name scen: '52 week share price'!#REF!
Name scen: Comps!#REF!
Name scen: 'DCF model'!$E$16
Name Tax_shield: WACC!$D$18
Name Tax_shielf: WACC!$D$18
Name Tgr: '52 week share price'!#REF!
Name Tgr: Comps!#REF!
Name tgr: 'DCF model'!$E$18
Name wacc: '52 week share price'!#REF!
Name wacc: Comps!#REF!
Name wacc: 'DCF model'!$E$17

Sheet Valuation
C3: VALUATION
C5: Adobe Inc. (NASDAQ: ADBE)
C6: Share Price [as of 02/09/2026] | D6: ='DCF model'!E11 -> 254.14
C7: Shares Out. | D7: ='IS - ADOBE'!F25 -> 426.2
C8: Market Cap | D8: =D6*D7 -> 108314.47
C9: Cash | D9: ='DCF model'!O104 -> 5431
C10: Debt | D10: =-'DCF model'!O105 -> 6210
C11: TEV | D11: =D8-D9-D10 -> 96673.468
C13: DCF Valuation Summary
C14: PV of FCFs | D14: =SUM('DCF model'!M98:O98) -> 23242.217
C15: PV of TV | D15: ='DCF model'!O101 -> 103617.3
C16: Implied Enterprise Value | D16: =D14+D15 -> 126859.52
C17: (+) Cash | D17: ='DCF model'!O104 -> 5431
C18: (-) Debt | D18: =-'DCF model'!O105 -> 6210
C19: Implied Equity Value | D19: =D16+D17-D18 -> 126080.52
C20: Shares Out. | D20: ='DCF model'!O76 -> 391.58082
C21: 3-Year Price Target | D21: =D19/D20 -> 321.97828
C23: Return Profile
C24: Total Upside / Downside | D24: =D21/D6-1 -> 0.26693273
C25: Implied IRR | D25: =(D21/D6)^(1/3)-1 -> 0.082059607

Sheet Scenarios
C3: SCENARIOS
D5: Base | E5: Bull | F5: Bear
D6: FY2028 | E6: FY2028 | F6: FY2028
C7: Revenue (Mln) | D7: 32089.57 | E7: 33957.796 | F7: 27949.45
C8: 3yr Growth | D8: 0.10522575 | E8: 0.126 | F8: ='DCF model'!O28 -> 0.04788127
C10: EBITDA | D10: 12857.969 | E10: 14286.876 | F10: 10079.158
C11: Margin | D11: =D10/D$7 -> 0.40068997 | E11: =E10/E$7 -> 0.42072447 | F11: =F10/F$7 -> 0.36062098
C13: FCF | D13: 9882.8129 | E13: 10999.045 | F13: 7907.0454
C14: Margin | D14: =D13/D$7 -> 0.30797586 | E14: =E13/E$7 -> 0.32390338 | F14: =F13/F$7 -> 0.28290522
C15: Conversion | D15: =D13/D10 -> 0.76861384 | E15: =E13/E10 -> 0.76987055 | F15: =F13/F10 -> 0.78449464
C17: EV | D17: 127867.38 | E17: 157045.76 | F17: 91770.449
C18: Net Debt | D18: -779 | E18: -779 | F18: -779
C19: Equity Value | D19: 127088.38 | E19: =E17-E18 -> 157824.76 | F19: =F17+F18 -> 90991.449
C20: Sh. Out. | D20: 391.58082 | E20: 391.58082 | F20: 413.54143
C21: Price Target | D21: =D19/D20 -> 324.55209 | E21: =E19/E20 -> 403.04517 | F21: =F19/F20 -> 220.02982
C23: Upside/Downside | D23: =D21/Valuation!$D$6-1 -> 0.27706026 | E23: =E21/Valuation!$D$6-1 -> 0.5859179 | F23: =F21/Valuation!$D$6-1 -> -0.13421805
C24: IRR | D24: =(1+D23)^(1/3)-1 -> 0.084935192 | E24: =(1+E23)^(1/3)-1 -> 0.16616562 | F24: =(1+F23)^(1/3)-1 -> -0.046905034
C25: Risk/Reward vs Bear Case | D25: =-D23/$F$23 -> 2.0642548 | E25: =-E23/$F$23 -> 4.365418

Sheet DCF model
C3: DCF model
A6: • | C6: Overview
C8: Comp name | E8: Adobe Inc. | G8: Valuation USD | I8: =R108 -> 418.12578 | K8: Valuation in 3Y | M8: =O108 -> 321.97828
C9: Ticker | E9: ADBE | G9: % delta vs current | I9: =I8/E11-1 -> 0.64525767 | K9: % delta vs current | M9: =M8/E11-1 -> 0.26693273
C10: Date | E10: 46076
C11: Price per share | E11: {=_xlfn.STOCKHISTORY(E9,E10,E10,0,0,2)} -> 254.14
A13: • | C13: Assumptions
C15: Triggers | G15: Conservative | H15: Year | I15: Amount | K15: Base / Street | L15: Year | M15: Amount | O15: Optimistic | P15: Year | Q15: Amount
C16: Scenario | E16: 1 | G16: Revenue gr | H16: 26-'31 | I16: -0.4 | O16: Revenue gr | P16: 26-'31 | Q16: 0.2
C17: WACC | E17: =CHOOSE(scen,M18,I18,Q18) -> 0.10280515 | G17: EBITDA margin | H17: 26-'31 | I17: -0.1 | O17: EBITDA margin | P17: 26-'31 | Q17: 0.05
C18: TGR | E18: =CHOOSE(scen,M19,I19,Q19) -> 0.025 | G18: WACC | I18: =M18+0.75% -> 0.11030515 | K18: WACC | M18: =WACC!D21 -> 0.10280515 | O18: WACC | Q18: =M18-0.5% -> 0.097805146
G19: TGR | I19: 0.022 | K19: TGR | M19: 0.025 | O19: TGR | Q19: 0.028
A21: • | C21: Income statement
H23: Actuals | M23: Projections
C24: €M | H24: 2021 | I24: =+H24+1 -> 2022 | J24: =+I24+1 -> 2023 | K24: =+J24+1 -> 2024 | L24: =+K24+1 -> 2025 | M24: =+L24+1 -> 2026 | N24: =+M24+1 -> 2027 | O24: =+N24+1 -> 2028 | P24: =+O24+1 -> 2029 | ... R24: =+Q24+1 -> 2031
C25: Revenue | H25: ='IS - ADOBE'!B4 -> 15785 | I25: ='IS - ADOBE'!C4 -> 17606 | J25: ='IS - ADOBE'!D4 -> 19409 | K25: ='IS - ADOBE'!E4 -> 21505 | L25: ='IS - ADOBE'!F4 -> 23769 | M25: =L25*(1+M26) -> 26270.111 | N25: =M25*(1+N26) -> 29034.403 | O25: =N25*(1+O26) -> 32089.57 | P25: =O25*(1+P26) -> 35466.219 | Q25: =P25*(1+Q26) -> 39198.178 | R25: =Q25*(1+R26) -> 43322.836
C26: % growth | I26: =I25/H25-1 -> 0.11536269 | J26: =J25/I25-1 -> 0.10240827 | K26: =K25/J25-1 -> 0.10799114 | L26: =L25/K25-1 -> 0.10527784 | M26: =OFFSET(M26,scen,0) -> 0.10522575 | N26: =OFFSET(N26,scen,0) -> 0.10522575 | O26: =OFFSET(O26,scen,0) -> 0.10522575 | P26: =OFFSET(P26,scen,0) -> 0.10522575 | Q26: =OFFSET(Q26,scen,0) -> 0.10522575 | R26: =OFFSET(R26,scen,0) -> 0.10522575
C27: 1. Base | M27: =AVERAGE(J26:L26) -> 0.10522575 | N27: =M27 -> 0.10522575 | O27: =N27 -> 0.10522575 | P27: =O27 -> 0.10522575 | Q27: =P27 -> 0.10522575 | R27: =Q27 -> 0.10522575
C28: 2. Conservative | M28: =M27*(1+I16) -> 0.06313545 | N28: =M28-($M$28-$R$28)/($R$24-$M$24) -> 0.05550836 | O28: =N28-($M$28-$R$28)/($R$24-$M$24) -> 0.04788127 | P28: =O28-($M$28-$R$28)/($R$24-$M$24) -> 0.04025418 | Q28: =P28-($M$28-$R$28)/($R$24-$M$24) -> 0.03262709 | R28: 0.025
C29: 3. Optimistic | M29: =M27*(1+Q16) -> 0.1262709 | N29: =M29 -> 0.1262709 | O29: =N29 -> 0.1262709 | P29: =O29 -> 0.1262709 | Q29: =P29 -> 0.1262709 | R29: =Q29 -> 0.1262709
C31: COGS | H31: ='IS - ADOBE'!B6*-1 -> -1865 | I31: ='IS - ADOBE'!C6*-1 -> -2165 | J31: ='IS - ADOBE'!D6*-1 -> -2354 | K31: ='IS - ADOBE'!E6*-1 -> -2358 | L31: ='IS - ADOBE'!F6*-1 -> -2551 | M31: =M33-M25 -> -2772.5295 | N31: =N33-N25 -> -3012.3308 | O31: =O33-O25 -> -3271.785 | P31: =P33-P25 -> -3552.3607 | Q31: =Q33-Q25 -> -3855.6165 | R31: =R33-R25 -> -4183.2036
C33: Gross profit | H33: =H25+H31 -> 13920 | I33: =I25+I31 -> 15441 | J33: =J25+J31 -> 17055 | K33: =K25+K31 -> 19147 | L33: =L25+L31 -> 21218 | M33: =M25*M34 -> 23497.581 | N33: =N25*N34 -> 26022.072 | O33: =O25*O34 -> 28817.785 | P33: =P25*P34 -> 31913.858 | Q33: =Q25*Q34 -> 35342.562 | R33: =R25*R34 -> 39139.632
C34: % margin | H34: =H33/H$25 -> 0.88184986 | I34: =I33/I$25 -> 0.87703056 | J34: =J33/J$25 -> 0.87871606 | K34: =K33/K$25 -> 0.89035108 | L34: =L33/L$25 -> 0.89267533 | M34: =L34*(1+M35) -> 0.89446068 | N34: =M34*(1+N35) -> 0.89624961 | O34: =N34*(1+O35) -> 0.8980421 | P34: =O34*(1+P35) -> 0.89983819 | Q34: =P34*(1+Q35) -> 0.90163787 | R34: =Q34*(1+R35) -> 0.90344114
C35: % growth | I35: =I34/H34-1 -> -0.0054649889 | J35: =J34/I34-1 -> 0.0019218279 | K35: =K34/J34-1 -> 0.013240934 | L35: =L34/K34-1 -> 0.0026104896 | M35: =OFFSET(M35,scen,0) -> 0.002 | N35: =OFFSET(N35,scen,0) -> 0.002 | O35: =OFFSET(O35,scen,0) -> 0.002 | P35: =OFFSET(P35,scen,0) -> 0.002 | Q35: =OFFSET(Q35,scen,0) -> 0.002 | R35: =OFFSET(R35,scen,0) -> 0.002
C36: 1. Base | M36: 0.002 | N36: =M36 -> 0.002 | O36: =N36 -> 0.002 | P36: =O36 -> 0.002 | Q36: =P36 -> 0.002 | R36: =Q36 -> 0.002
C37: 2. Conservative | M37: -0.005 | N37: =M37 -> -0.005 | O37: =N37 -> -0.005 | P37: =O37 -> -0.005 | Q37: =P37 -> -0.005 | R37: =Q37 -> -0.005
C38: 3. Optimistic | M38: 0.003 | N38: =M38 -> 0.003 | O38: =N38 -> 0.003 | P38: =O38 -> 0.003 | Q38: =P38 -> 0.003 | R38: =Q38 -> 0.003
C40: Opex | H40: =('IS - ADOBE'!B14-'CF - ADOBE'!B6)*-1 -> -7330 | I40: =('IS - ADOBE'!C14-'CF - ADOBE'!C6)*-1 -> -8487 | J40: =('IS - ADOBE'!D14-'CF - ADOBE'!D6)*-1 -> -9533 | K40: =('IS - ADOBE'!E14-'CF - ADOBE'!E6)*-1 -> -11549 | L40: =('IS - ADOBE'!F14-'CF - ADOBE'!F6)*-1 -> -11694 | M40: =M43-M33 -> -12971.411 | N40: =N43-N33 -> -14388.278 | O40: =O43-O33 -> -15959.816 | P40: =P43-P33 -> -17702.9 | Q40: =Q43-Q33 -> -19636.245 | R40: =R43-R33 -> -21780.606
C41: % sales | H41: =H40/H25*-1 -> 0.4643649 | I41: =I40/I25*-1 -> 0.48205157 | J41: =J40/J25*-1 -> 0.49116389 | K41: =K40/K25*-1 -> 0.5370379 | L41: =L40/L25*-1 -> 0.49198536 | M41: =M40/M25*-1 -> 0.49377071 | N41: =N40/N25*-1 -> 0.49555963 | O41: =O40/O25*-1 -> 0.49735213 | ... R41: =R40/R25*-1 -> 0.50275117
C43: EBITDA | H43: =H33+H40 -> 6590 | I43: =I33+I40 -> 6954 | J43: =J33+J40 -> 7522 | K43: =K33+K40 -> 7598 | L43: =L33+L40 -> 9524 | M43: =M25*M44 -> 10526.17 | N43: =N25*N44 -> 11633.794 | O43: =O25*O44 -> 12857.969 | P43: =P25*P44 -> 14210.958 | Q43: =Q25*Q44 -> 15706.317 | R43: =R25*R44 -> 17359.026
C44: % margin | H44: =H43/H$25 -> 0.41748495 | I44: =I43/I$25 -> 0.39497898 | J44: =J43/J$25 -> 0.38755217 | K44: =K43/K$25 -> 0.35331318 | L44: =L43/L$25 -> 0.40068997 | M44: =OFFSET(M44,scen,0) -> 0.40068997 | N44: =OFFSET(N44,scen,0) -> 0.40068997 | O44: =OFFSET(O44,scen,0) -> 0.40068997 | P44: =OFFSET(P44,scen,0) -> 0.40068997 | Q44: =OFFSET(Q44,scen,0) -> 0.40068997 | R44: =OFFSET(R44,scen,0) -> 0.40068997
C45: 1. Base | M45: =L44 -> 0.40068997 | N45: =M45 -> 0.40068997 | O45: =N45 -> 0.40068997 | P45: =O45 -> 0.40068997 | Q45: =P45 -> 0.40068997 | R45: =Q45 -> 0.40068997
C46: 2. Conservative | M46: =M45*(1+I17) -> 0.36062098 | N46: =M46 -> 0.36062098 | O46: =N46 -> 0.36062098 | P46: =O46 -> 0.36062098 | Q46: =P46 -> 0.36062098 | R46: =Q46 -> 0.36062098
C47: 3. Optimistic | M47: =M45*(1+Q17) -> 0.42072447 | N47: =M47 -> 0.42072447 | O47: =N47 -> 0.42072447 | P47: =O47 -> 0.42072447 | Q47: =P47 -> 0.42072447 | R47: =Q47 -> 0.42072447
C49: D&A | H49: ='CF - ADOBE'!B6*-1 -> -788 | I49: ='CF - ADOBE'!C6*-1 -> -856 | J49: ='CF - ADOBE'!D6*-1 -> -872 | K49: ='CF - ADOBE'!E6*-1 -> -857 | L49: ='CF - ADOBE'!F6*-1 -> -818 | M49: =M25*M50*-1 -> -788.10333 | N49: =N25*N50*-1 -> -871.03209 | O49: =O25*O50*-1 -> -962.68709 | P49: =P25*P50*-1 -> -1063.9866 | Q49: =Q25*Q50*-1 -> -1175.9454 | R49: =R25*R50*-1 -> -1299.6851
C50: % sales | H50: =H49/H$25*-1 -> 0.049920811 | I50: =I49/I$25*-1 -> 0.048619789 | J50: =J49/J$25*-1 -> 0.044927611 | K50: =K49/K$25*-1 -> 0.039851197 | L50: =L49/L$25*-1 -> 0.034414574 | M50: =OFFSET(M50,scen,0) -> 0.03 | N50: =OFFSET(N50,scen,0) -> 0.03 | O50: =OFFSET(O50,scen,0) -> 0.03 | P50: =OFFSET(P50,scen,0) -> 0.03 | Q50: =OFFSET(Q50,scen,0) -> 0.03 | R50: =OFFSET(R50,scen,0) -> 0.03
C51: 1. Base | M51: 0.03 | N51: =M51 -> 0.03 | O51: =N51 -> 0.03 | P51: =O51 -> 0.03 | Q51: =P51 -> 0.03 | R51: =Q51 -> 0.03
C52: 2. Conservative | M52: 0.03 | N52: =M52 -> 0.03 | O52: =N52 -> 0.03 | P52: =O52 -> 0.03 | Q52: =P52 -> 0.03 | R52: =Q52 -> 0.03
C53: 3. Optimistic | M53: 0.03 | N53: =M53 -> 0.03 | O53: =N53 -> 0.03 | P53: =O53 -> 0.03 | Q53: =P53 -> 0.03 | R53: =Q53 -> 0.03
C55: Capex | H55: ='CF - ADOBE'!B25 -> -348 | I55: ='CF - ADOBE'!C25 -> -442 | J55: ='CF - ADOBE'!D25 -> -360 | K55: ='CF - ADOBE'!E25 -> -183 | L55: ='CF - ADOBE'!F25 -> -179 | M55: =M25*M56*-1 -> -302.88179 | N55: =N25*N56*-1 -> -334.75276 | O55: =O25*O56*-1 -> -369.97736 | P55: =P25*P56*-1 -> -408.90851 | Q55: =Q25*Q56*-1 -> -451.93622 | R55: =R25*R56*-1 -> -499.49154
C56: % sales | H56: =H55/H$25*-1 -> 0.022046246 | I56: =I55/I$25*-1 -> 0.025105078 | J56: =J55/J$25*-1 -> 0.018548096 | K56: =K55/K$25*-1 -> 0.0085096489 | L56: =L55/L$25*-1 -> 0.0075308175 | M56: =OFFSET(M56,scen,0) -> 0.011529521 | N56: =OFFSET(N56,scen,0) -> 0.011529521 | O56: =OFFSET(O56,scen,0) -> 0.011529521 | P56: =OFFSET(P56,scen,0) -> 0.011529521 | Q56: =OFFSET(Q56,scen,0) -> 0.011529521 | R56: =OFFSET(R56,scen,0) -> 0.011529521
C57: 1. Base | M57: =AVERAGE(J56:L56) -> 0.011529521 | N57: =M57 -> 0.011529521 | O57: =N57 -> 0.011529521 | P57: =O57 -> 0.011529521 | Q57: =P57 -> 0.011529521 | R57: =Q57 -> 0.011529521
C58: 2. Conservative | M58: 0.01 | N58: =M58 -> 0.01 | O58: =N58 -> 0.01 | P58: =O58 -> 0.01 | Q58: =P58 -> 0.01 | R58: =Q58 -> 0.01
C59: 3. Optimistic | M59: 0.01 | N59: =M59 -> 0.01 | O59: =N59 -> 0.01 | P59: =O59 -> 0.01 | Q59: =P59 -> 0.01 | R59: =Q59 -> 0.01
C61: EBIT | H61: =H43+H49 -> 5802 | I61: =I43+I49 -> 6098 | J61: =J43+J49 -> 6650 | K61: =K43+K49 -> 6741 | L61: =L43+L49 -> 8706 | M61: =M43+M49 -> 9738.0667 | N61: =N43+N49 -> 10762.762 | O61: =O43+O49 -> 11895.282 | ... R61: =R43+R49 -> 16059.341
C62: % margin | H62: =H61/H$25 -> 0.36756414 | I62: =I61/I$25 -> 0.3463592 | J62: =J61/J$25 -> 0.34262456 | K62: =K61/K$25 -> 0.31346199 | L62: =L61/L$25 -> 0.3662754 | M62: =M61/M$25 -> 0.37068997 | N62: =N61/N$25 -> 0.37068997 | O62: =O61/O$25 -> 0.37068997 | ... R62: =R61/R$25 -> 0.37068997
C64: Interests | H64: ='IS - ADOBE'!B17 -> -113 | I64: ='IS - ADOBE'!C17 -> -112 | J64: ='IS - ADOBE'!D17 -> -113 | K64: ='IS - ADOBE'!E17 -> -169 | L64: ='IS - ADOBE'!F17 -> -263 | M64: =M25*M65*-1 -> -290.67437 | N64: =N25*N65*-1 -> -321.2608 | O64: =O25*O65*-1 -> -355.06571 | P64: =P25*P65*-1 -> -392.42777 | Q64: =Q25*Q65*-1 -> -433.72127 | R64: =R25*R65*-1 -> -479.35992
C65: % sales | H65: =H64/H25*-1 -> 0.007158695 | I65: =I64/I25*-1 -> 0.0063614677 | J65: =J64/J25*-1 -> 0.0058220413 | K65: =K64/K25*-1 -> 0.0078586375 | L65: =L64/L25*-1 -> 0.011064832 | M65: =L65 -> 0.011064832 | N65: =M65 -> 0.011064832 | O65: =N65 -> 0.011064832 | P65: =O65 -> 0.011064832 | Q65: =P65 -> 0.011064832 | R65: =Q65 -> 0.011064832
C67: Taxable income | H67: =H61+H64 -> 5689 | I67: =I61+I64 -> 5986 | J67: =J61+J64 -> 6537 | K67: =K61+K64 -> 6572 | L67: =L61+L64 -> 8443 | M67: =M61+M64 -> 9447.3923 | N67: =N61+N64 -> 10441.501 | O67: =O61+O64 -> 11540.216 | ... R67: =R61+R64 -> 15579.981
C68: % margin | H68: =H67/H$25 -> 0.36040545 | I68: =I67/I$25 -> 0.33999773 | J68: =J67/J$25 -> 0.33680251 | K68: =K67/K$25 -> 0.30560335 | L68: =L67/L$25 -> 0.35521057 | M68: =M67/M$25 -> 0.35962514 | N68: =N67/N$25 -> 0.35962514 | O68: =O67/O$25 -> 0.35962514 | ... R68: =R67/R$25 -> 0.35962514
C70: Taxes | H70: ='IS - ADOBE'!B22*-1 -> -883 | I70: ='IS - ADOBE'!C22*-1 -> -1252 | J70: ='IS - ADOBE'!D22*-1 -> -1371 | K70: ='IS - ADOBE'!E22*-1 -> -1371 | L70: ='IS - ADOBE'!F22*-1 -> -1604 | M70: =M67*M71*-1 -> -1837.8728 | N70: =N67*N71*-1 -> -2031.2644 | O70: =O67*O71*-1 -> -2245.0057 | P70: =P67*P71*-1 -> -2481.2381 | Q70: =Q67*Q71*-1 -> -2742.3283 | R70: =R67*R71*-1 -> -3030.8918
C71: % tax rate | H71: =H70/H67*-1 -> 0.15521181 | I71: =I70/I67*-1 -> 0.20915469 | J71: =J70/J67*-1 -> 0.20972923 | K71: =K70/K67*-1 -> 0.20861229 | L71: =L70/L67*-1 -> 0.18997986 | M71: =AVERAGE(H71:L71) -> 0.19453758 | N71: =M71 -> 0.19453758 | O71: =N71 -> 0.19453758 | P71: =O71 -> 0.19453758 | Q71: =P71 -> 0.19453758 | R71: =Q71 -> 0.19453758
C73: Net income | H73: =H67+H70 -> 4806 | I73: =I67+I70 -> 4734 | J73: =J67+J70 -> 5166 | K73: =K67+K70 -> 5201 | L73: =L67+L70 -> 6839 | M73: =M67+M70 -> 7609.5195 | N73: =N67+N70 -> 8410.2369 | O73: =O67+O70 -> 9295.2104 | ... R73: =R67+R70 -> 12549.089
C74: % margin | H74: =H73/H$25 -> 0.30446627 | I74: =I73/I$25 -> 0.26888561 | J74: =J73/J$25 -> 0.26616518 | K74: =K73/K$25 -> 0.24185073 | L74: =L73/L$25 -> 0.28772771 | M74: =M73/M$25 -> 0.28966454 | N74: =N73/N$25 -> 0.28966454 | O74: =O73/O$25 -> 0.28966454 | ... R74: =R73/R$25 -> 0.28966454
C76: Shares Out. | H76: ='IS - ADOBE'!B25 -> 477.3 | I76: ='IS - ADOBE'!C25 -> 469.5 | J76: ='IS - ADOBE'!D25 -> 457.1 | K76: ='IS - ADOBE'!E25 -> 447.1 | L76: ='IS - ADOBE'!F25 -> 426.2 | M76: =L76*(1+M77) -> 414.33291 | N76: =M76*(1+N77) -> 402.79626 | O76: =N76*(1+O77) -> 391.58082 | P76: =O76*(1+P77) -> 380.67767 | Q76: =P76*(1+Q77) -> 370.07811 | R76: =Q76*(1+R77) -> 359.77367
C77: % growth | I77: =I76/H76-1 -> -0.016341923 | J77: =J76/I76-1 -> -0.026411076 | K77: =K76/J76-1 -> -0.021877051 | L77: =L76/K76-1 -> -0.046745694 | M77: =OFFSET(M77,scen,0) -> -0.027843936 | N77: =OFFSET(N77,scen,0) -> -0.027843936 | O77: =OFFSET(O77,scen,0) -> -0.027843936 | P77: =OFFSET(P77,scen,0) -> -0.027843936 | Q77: =OFFSET(Q77,scen,0) -> -0.027843936 | R77: =OFFSET(R77,scen,0) -> -0.027843936
C78: 1. Base | M78: =AVERAGE(I77:L77) -> -0.027843936 | N78: =M78 -> -0.027843936 | O78: =N78 -> -0.027843936 | P78: =O78 -> -0.027843936 | Q78: =P78 -> -0.027843936 | R78: =Q78 -> -0.027843936
C79: 2. Conservative | M79: -0.01 | N79: =M79 -> -0.01 | O79: =N79 -> -0.01 | P79: =O79 -> -0.01 | Q79: =P79 -> -0.01 | R79: =Q79 -> -0.01
C80: 3. Optimistic | M80: -0.04 | N80: =M80 -> -0.04 | O80: =N80 -> -0.04 | P80: =O80 -> -0.04 | Q80: =P80 -> -0.04 | R80: =Q80 -> -0.04
A82: • | C82: DCF
H84: Actuals | M84: Projections
C85: €M | H85: 2021 | I85: =+H85+1 -> 2022 | J85: =+I85+1 -> 2023 | K85: =+J85+1 -> 2024 | L85: =+K85+1 -> 2025 | M85: =+L85+1 -> 2026 | N85: =+M85+1 -> 2027 | O85: =+N85+1 -> 2028 | P85: =+O85+1 -> 2029 | ... R85: =+Q85+1 -> 2031
C86: EBIT | M86: =M61 -> 9738.0667 | N86: =N61 -> 10762.762 | O86: =O61 -> 11895.282 | P86: =P61 -> 13146.972 | Q86: =Q61 -> 14530.372 | R86: =R61 -> 16059.341
C87: (1-Tax) | M87: =(1-M71) -> 0.80546242 | N87: =(1-N71) -> 0.80546242 | O87: =(1-O71) -> 0.80546242 | P87: =(1-P71) -> 0.80546242 | Q87: =(1-Q71) -> 0.80546242 | R87: =(1-R71) -> 0.80546242
C88: EBIAT (or NOPAT) | M88: =M86*M87 -> 7843.6468 | N88: =N86*N87 -> 8669.0004 | O88: =O86*O87 -> 9581.2025 | P88: =P86*P87 -> 10589.392 | Q88: =Q86*Q87 -> 11703.668 | R88: =R86*R87 -> 12935.196
C89: Plus D&A | M89: =-M49 -> 788.10333 | N89: =-N49 -> 871.03209 | O89: =-O49 -> 962.68709 | P89: =-P49 -> 1063.9866 | Q89: =-Q49 -> 1175.9454 | R89: =-R49 -> 1299.6851
C90: Less Capex | M90: =M55 -> -302.88179 | N90: =N55 -> -334.75276 | O90: =O55 -> -369.97736 | P90: =P55 -> -408.90851 | Q90: =Q55 -> -451.93622 | R90: =R55 -> -499.49154
C91: Less Change in WC | M91: =-M161 -> -487.51076 | N91: =-N161 -> -262.55914 | O91: =-O161 -> -291.0993 | P91: =-P161 -> -322.74062 | Q91: =-Q161 -> -357.81996 | R91: =-R161 -> -396.71073
C92: Free Cash Flow | M92: =SUM(M88:M91) -> 7841.3576 | N92: =SUM(N88:N91) -> 8942.7206 | O92: =SUM(O88:O91) -> 9882.8129 | P92: =SUM(P88:P91) -> 10921.729 | Q92: =SUM(Q88:Q91) -> 12069.858 | R92: =SUM(R88:R91) -> 13338.678
C94: Discount period not corrected | M94: 1 | N94: =M94+1 -> 2 | O94: =N94+1 -> 3 | P94: =O94+1 -> 4 | Q94: =P94+1 -> 5 | R94: =Q94+1 -> 6
C95: Fraction of year left | M95: =1-(2/12) -> 0.83333333 | N95: =M95+1 -> 1.8333333 | O95: =N95+1 -> 2.8333333 | P95: =O95+1 -> 3.8333333 | Q95: =P95+1 -> 4.8333333 | R95: =Q95+1 -> 5.8333333
C96: Mid year convention DP | M96: =M95*0.5 -> 0.41666667 | N96: =M95+0.5 -> 1.3333333 | O96: =N96+1 -> 2.3333333 | P96: =O96+1 -> 3.3333333 | Q96: =P96+1 -> 4.3333333 | R96: =Q96+1 -> 5.3333333
C98: Discounted FCF | M98: =M92/(1+wacc)^M96 -> 7528.0662 | N98: =N92/(1+wacc)^N96 -> 7848.8245 | O98: =O92/(1+wacc)^O96 -> 7865.3263 | P98: =P92/(1+wacc)^P96 -> 7881.8613 | Q98: =Q92/(1+wacc)^Q96 -> 7898.4295 | R98: =R92/(1+wacc)^R96 -> 7915.031
C100: Terminal value | O100: {=(O92*(1+tgr))/(wacc-tgr)} -> 130195.54 | R100: {=(R92*(1+tgr))/(wacc-tgr)} -> 175722.89
C101: Discounted TV | O101: =O100/(1+wacc)^O96 -> 103617.3 | R101: =R100/(1+wacc)^R96 -> 104272.11
C103: Enterprise value | O103: =O101+SUM(M98:O98) -> 126859.52 | R103: =R101+SUM(M98:R98) -> 151209.65
C104: Plus Cash | O104: ='BS - ADOBE'!$F$4 -> 5431 | R104: ='BS - ADOBE'!$F$4 -> 5431
C105: Less Debt | O105: =-D -> -6210 | R105: =-D -> -6210
C106: Equity value | O106: =SUM(O103:O105) -> 126080.52 | R106: =SUM(R103:R105) -> 150430.65
C107: Number of shares | O107: =O76 -> 391.58082 | R107: =R76 -> 359.77367
C108: Price per share | O108: =O106/O107 -> 321.97828 | R108: =R106/R107 -> 418.12578
A110: • | C110: Sensitivity analysis
C112: Dynamic | F112: WACC
E113: =R108 -> 418.12578 | F113: 0.09 | G113: =F113+0.25% -> 0.0925 | H113: =G113+0.25% -> 0.095 | I113: =H113+0.25% -> 0.0975 | J113: =I113+0.25% -> 0.1 | K113: =J113+0.25% -> 0.1025 | L113: =K113+0.25% -> 0.105
D114: TGR | E114: 0.02 | F114: 473.94592 | G114: 457.28771 | H114: 441.74604 | I114: 427.21279 | J114: 413.59335 | K114: 400.80457 | L114: 388.77308
E115: =E114+0.25% -> 0.0225 | F115: 487.44922 | G115: 469.73556 | H115: 453.24953 | I115: 437.8683 | J115: 423.48488 | K115: 410.00565 | L115: 397.34834
E116: =E115+0.25% -> 0.025 | F116: 501.99125 | G116: 483.10548 | H116: 465.5747 | I116: 449.25867 | J116: 434.03584 | K116: 419.80035 | L116: 406.45956
E117: =E116+0.25% -> 0.0275 | F117: 517.69663 | G117: 497.50385 | H117: 478.81285 | I117: 461.46264 | J117: 445.31446 | K117: 430.24803 | L117: 416.15859
E118: =E117+0.25% -> 0.03 | F118: 534.7108 | G118: 513.05409 | H118: 493.06931 | I118: 474.57061 | J118: 457.39869 | K118: 441.41624 | L118: 426.50423
C121: Base case | F121: WACC
E122: 270.50981 | F122: 0.06 | G122: 0.0625 | H122: 0.065 | I122: 0.0675 | J122: 0.07 | K122: 0.0725 | L122: 0.075
D123: TGR | E123: 0.02 | F123: 245.59545 | G123: 228.00046 | H123: 212.35986 | I123: 198.36507 | J123: 185.76923 | K123: 174.37247 | L123: 164.01131
E124: 0.0225 | F124: 262.85243 | G124: 243.09328 | H124: 225.65799 | I124: 210.15924 | J124: 196.29127 | K124: 183.80947 | L124: 172.51581
E125: 0.025 | F125: 282.57469 | G125: 260.19848 | H125: 240.61838 | I125: 223.34095 | J125: 207.98243 | K125: 194.23984 | L125: 181.87077
E126: 0.0275 | F126: 305.33114 | G126: 279.74728 | H126: 257.57349 | I126: 238.17039 | J126: 221.04903 | K126: 205.82913 | L126: 192.21047
E127: 0.03 | F127: 331.88034 | G127: 302.30359 | H127: 276.95076 | I127: 254.97707 | J127: 235.74894 | K127: 218.78187 | L127: 203.69901
C130: Conservative case | F130: WACC
E131: 176.75668 | F131: 0.06 | G131: 0.0625 | H131: 0.065 | I131: 0.0675 | J131: 0.07 | K131: 0.0725 | L131: 0.075
D132: TGR | E132: 0.02 | F132: 178.30692 | G132: 164.79069 | H132: 152.77418 | I132: 142.02059 | J132: 132.3405 | K132: 123.58058 | L132: 115.61537
E133: 0.0225 | F133: 191.54799 | G133: 176.37124 | H133: 162.97767 | I133: 151.07011 | J133: 140.41394 | K133: 130.82148 | L133: 122.14078
...

Sheet Comps
C3: Comps
A6: • | C6: Comps
C7: all values in B USD
C9: Name | D9: Employees | E9: Revenue | F9: Rev growth | G9: EBITDA | H9: EBITDA % | I9: Net Income | J9: NI % | K9: Price / share | L9: Market Cap | M9: EV | N9: EV / Revenue | O9: EV / EBITDA | P9: P / Sales | Q9: P / E | R9: Selected?
C10: McDonald's | D10: 150000 | E10: 26.27 | F10: 0.0125 | G10: 14.33 | H10: =G10/E10 -> 0.54548915 | I10: 8.41 | J10: =I10/E10 -> 0.32013704 | K10: 302.11 | L10: 216.86 | M10: 270.85
C11: Tyson Foods | D11: 133000 | E11: 54.44 | F11: 0.0212 | G11: 2.51 | H11: =G11/E11 -> 0.046105805 | I11: 0.474 | J11: =I11/E11 -> 0.0087068332 | K11: 56.93 | L11: 19.32 | M11: 26.97 | N11: =M11/E11 -> 0.49540779 | O11: =M11/G11 -> 10.74502 | P11: =L11/E11 -> 0.35488611 | Q11: =L11/I11 -> 40.759494 | R11: X
C12: Starbucks | D12: 381000 | E12: 37.18 | F12: 0.0279 | G12: 4.71 | H12: =G12/E12 -> 0.12668101 | I12: 1.86 | J12: =I12/E12 -> 0.050026896 | K12: 89.15 | L12: 96.16 | M12: 119.55 | N12: =M12/E12 -> 3.2154384 | O12: =M12/G12 -> 25.382166 | P12: =L12/E12 -> 2.5863367 | Q12: =L12/I12 -> 51.698925
C13: Chipotle | D13: 130000 | E13: 11.79 | F13: 0.0731 | G13: 2.28 | H13: =G13/E13 -> 0.19338422 | I13: 1.54 | J13: =I13/E13 -> 0.13061917 | K13: 38.91 | L13: 52.55 | M13: 55.78 | N13: =M13/E13 -> 4.7311281 | O13: =M13/G13 -> 24.464912 | P13: =L13/E13 -> 4.4571671 | Q13: =L13/I13 -> 34.123377 | R13: X
C14: Burger King | D14: 6000
C15: KFC | E15: 33.36
C16: Domino's Pizza | D16: 10700 | E16: 4.85 | F16: 0.0392 | G16: 1.03 | H16: =G16/E16 -> 0.21237113 | I16: 0.5 | J16: =I16/E16 -> 0.10309278 | K16: 412.22 | L16: 14.66 | M16: 19.59 | N16: =M16/E16 -> 4.0391753 | O16: =M16/G16 -> 19.019417 | P16: =L16/E16 -> 3.0226804 | Q16: =L16/I16 -> 29.32 | R16: X
C17: Jack In The Box | D17: 5046 | E17: 1.47 | F17: -0.0675 | G17: 0.034 | H17: =G17/E17 -> 0.023129252 | I17: -0.08 | J17: =I17/E17 -> -0.054421769 | K17: 20.42 | L17: 0.373 | M17: 3.47
C18: Papa John's | D18: 11400 | E18: 2.09 | F18: -0.0064 | G18: 0.173 | H18: =G18/E18 -> 0.08277512 | I18: 0.038 | J18: =I18/E18 -> 0.018181818 | K18: 39.95 | L18: 1.58 | M18: 2.53 | N18: =M18/E18 -> 1.2105263 | O18: =M18/G18 -> 14.624277 | P18: =L18/E18 -> 0.75598086 | Q18: =L18/I18 -> 41.578947 | R18: X
C19: Subway
C20: Wendy's | D20: 14500 | E20: 2.21 | F20: -0.0021 | G20: 0.552 | H20: =G20/E20 -> 0.24977376 | I20: 0.186 | J20: =I20/E20 -> 0.084162896 | K20: 8.35 | L20: 1.75 | M20: 5.55 | N20: =M20/E20 -> 2.5113122 | O20: =M20/G20 -> 10.054348 | P20: =L20/E20 -> 0.7918552 | Q20: =L20/I20 -> 9.4086022
C21: Chick-fil-A
C22: Shake Shack | D22: 12826 | E22: 1.37 | F22: 0.1349 | G22: 0.174 | H22: =G22/E22 -> 0.1270073 | I22: 0.042 | J22: =I22/E22 -> 0.030656934 | K22: 89.6 | L22: 3.77 | M22: 4.29 | N22: =M22/E22 -> 3.1313869 | O22: =M22/G22 -> 24.655172 | P22: =L22/E22 -> 2.7518248 | Q22: =L22/I22 -> 89.761905 | R22: X
C23: Mean | D23: {=AVERAGE(IF($R$11:$R$22="X",D11:D22))} -> 59585.2 | E23: {=AVERAGE(IF($R$11:$R$22="X",E11:E22))} -> 14.908 | F23: {=AVERAGE(IF($R$11:$R$22="X",F11:F22))} -> 0.0524 | G23: {=AVERAGE(IF($R$11:$R$22="X",G11:G22))} -> 1.2334 | H23: {=AVERAGE(IF($R$11:$R$22="X",H11:H22))} -> 0.13232872 | I23: {=AVERAGE(IF($R$11:$R$22="X",I11:I22))} -> 0.5188 | J23: {=AVERAGE(IF($R$11:$R$22="X",J11:J22))} -> 0.058251508 | K23: {=AVERAGE(IF($R$11:$R$22="X",K11:K22))} -> 127.522 | ... Q23: {=AVERAGE(IF($R$11:$R$22="X",Q11:Q22))} -> 47.108744
C24: Median | D24: {=MEDIAN(IF($R$11:$R$22="X",D11:D22))} -> 12826 | E24: {=MEDIAN(IF($R$11:$R$22="X",E11:E22))} -> 4.85 | F24: {=MEDIAN(IF($R$11:$R$22="X",F11:F22))} -> 0.0392 | G24: {=MEDIAN(IF($R$11:$R$22="X",G11:G22))} -> 1.03 | H24: {=MEDIAN(IF($R$11:$R$22="X",H11:H22))} -> 0.1270073 | I24: {=MEDIAN(IF($R$11:$R$22="X",I11:I22))} -> 0.474 | J24: {=MEDIAN(IF($R$11:$R$22="X",J11:J22))} -> 0.030656934 | K24: {=MEDIAN(IF($R$11:$R$22="X",K11:K22))} -> 56.93 | ... Q24: {=MEDIAN(IF($R$11:$R$22="X",Q11:Q22))} -> 40.759494
C25: 25th percentile | D25: {=PERCENTILE(IF($R$11:$R$22="X",D11:D22),0.25)} -> 11400 | E25: {=PERCENTILE(IF($R$11:$R$22="X",E11:E22),0.25)} -> 2.09 | F25: {=PERCENTILE(IF($R$11:$R$22="X",F11:F22),0.25)} -> 0.0212 | G25: {=PERCENTILE(IF($R$11:$R$22="X",G11:G22),0.25)} -> 0.174 | H25: {=PERCENTILE(IF($R$11:$R$22="X",H11:H22),0.25)} -> 0.08277512 | I25: {=PERCENTILE(IF($R$11:$R$22="X",I11:I22),0.25)} -> 0.042 | J25: {=PERCENTILE(IF($R$11:$R$22="X",J11:J22),0.25)} -> 0.018181818 | K25: {=PERCENTILE(IF($R$11:$R$22="X",K11:K22),0.25)} -> 39.95 | ... Q25: {=PERCENTILE(IF($R$11:$R$22="X",Q11:Q22),0.25)} -> 34.123377
C26: 75th percentile | D26: {=PERCENTILE(IF($R$11:$R$22="X",D11:D22),0.75)} -> 130000 | E26: {=PERCENTILE(IF($R$11:$R$22="X",E11:E22),0.75)} -> 11.79 | F26: {=PERCENTILE(IF($R$11:$R$22="X",F11:F22),0.75)} -> 0.0731 | G26: {=PERCENTILE(IF($R$11:$R$22="X",G11:G22),0.75)} -> 2.28 | H26: {=PERCENTILE(IF($R$11:$R$22="X",H11:H22),0.75)} -> 0.19338422 | I26: {=PERCENTILE(IF($R$11:$R$22="X",I11:I22),0.75)} -> 0.5 | J26: {=PERCENTILE(IF($R$11:$R$22="X",J11:J22),0.75)} -> 0.10309278 | K26: {=PERCENTILE(IF($R$11:$R$22="X",K11:K22),0.75)} -> 89.6 | ... Q26: {=PERCENTILE(IF($R$11:$R$22="X",Q11:Q22),0.75)} -> 41.578947
A28: • | C28: McD Valuation
N30: Equity value | R30: Price per share
C31: McDonald's | D31: Revenue | E31: EBITDA | F31: Net Income | G31: # Shares | H31: Cash | I31: Debt | J31: EV / Revenue | K31: EV / EBITDA | L31: P / Sales | M31: P / E | N31: EV / Revenue | O31: EV / EBITDA | P31: P / Sales | Q31: P / E | R31: EV / Revenue | S31: EV / EBITDA | T31: P / Sales | U31: P / E
C32: Mean | D32: =E10 -> 26.27 | E32: =G10 -> 14.33 | F32: =I10 -> 8.41 | G32: ='DCF model'!R107 -> 359.77367 | H32: ='DCF model'!R104/1000 -> 5.431 | I32: ='DCF model'!R105/1000 -> -6.21 | J32: =N23 -> 2.7215249 | K32: =O23 -> 18.70176 | L32: =P23 -> 2.2685079 | M32: =Q23 -> 47.108744 | N32: =J32*D32+H32+I32 -> 70.715458 | O32: =K32*E32+H32+I32 -> 267.21722 | P32: =L32*D32 -> 59.593701 | Q32: =M32*F32 -> 396.18454 | R32: =N32*1000/$G32 -> 196.5554 | S32: =O32*1000/$G32 -> 742.737 | T32: =P32*1000/$G32 -> 165.6422 | U32: =Q32*1000/$G32 -> 1101.2049
C33: Median | D33: =D32 -> 26.27 | E33: =E32 -> 14.33 | F33: =F32 -> 8.41 | G33: =G32 -> 359.77367 | H33: =H32 -> 5.431 | I33: =I32 -> -6.21 | J33: =N24 -> 3.1313869 | K33: =O24 -> 19.019417 | L33: =P24 -> 2.7518248 | M33: =Q24 -> 40.759494 | N33: =J33*D33+H33+I33 -> 81.482533 | O33: =K33*E33+H33+I33 -> 271.76925 | P33: =L33*D33 -> 72.290438 | Q33: =M33*F33 -> 342.78734 | R33: =N33*1000/$G33 -> 226.48275 | S33: =O33*1000/$G33 -> 755.38949 | T33: =P33*1000/$G33 -> 200.93309 | U33: =Q33*1000/$G33 -> 952.78606
C34: 25th percentile | D34: =D33 -> 26.27 | E34: =E33 -> 14.33 | F34: =F33 -> 8.41 | G34: =G33 -> 359.77367 | H34: =H33 -> 5.431 | I34: =I33 -> -6.21 | J34: =N25 -> 1.2105263 | K34: =O25 -> 14.624277 | L34: =P25 -> 0.75598086 | M34: =Q25 -> 34.123377 | N34: =J34*D34+H34+I34 -> 31.021526 | O34: =K34*E34+H34+I34 -> 208.7869 | P34: =L34*D34 -> 19.859617 | Q34: =M34*F34 -> 286.9776 | R34: =N34*1000/$G34 -> 86.225115 | S34: =O34*1000/$G34 -> 580.32844 | T34: =P34*1000/$G34 -> 55.200307 | U34: =Q34*1000/$G34 -> 797.66147
C35: 75th percentile | D35: =D34 -> 26.27 | E35: =E34 -> 14.33 | F35: =F34 -> 8.41 | G35: =G34 -> 359.77367 | H35: =H34 -> 5.431 | I35: =I34 -> -6.21 | J35: =N26 -> 4.0391753 | K35: =O26 -> 24.464912 | L35: =P26 -> 3.0226804 | M35: =Q26 -> 41.578947 | N35: =J35*D35+H35+I35 -> 105.33013 | O35: =K35*E35+H35+I35 -> 349.80319 | P35: =L35*D35 -> 79.405814 | Q35: =M35*F35 -> 349.67895 | R35: =N35*1000/$G35 -> 292.76776 | S35: =O35*1000/$G35 -> 972.28679 | T35: =P35*1000/$G35 -> 220.71046 | U35: =Q35*1000/$G35 -> 971.94145
A37: • | C37: End

Sheet INPUT>>>

Sheet WACC
C3: WACC
C5: WACC = kE*(E/E+D) + kd * D/D+E * (1-tax)
C6: Ke = Rf + Beta * (Rm - Rf)
C7: Rm - Rf = MRP
C9: Rf | D9: 0.04 | F9: 10-yr treas yield - google
C10: Beta | D10: 1.48 | F10: Yf
C11: MRP | D11: 0.045 | F11: Damodoran
C12: Ke | D12: =D9+D10*D11 -> 0.1066
C14: E | D14: 112411 | F14: Yf
C15: D | D15: ='BS - ADOBE'!F25 -> 6210 | F15: BS
C16: E% | D16: =E/(SUM(D14:D15)) -> 0.94764839
C17: D% | D17: =D/SUM(D14:D15) -> 0.052351607
C18: 1-Tax | D18: =(1-'DCF model'!M71) -> 0.80546242
C19: Kd | D19: =-'IS - ADOBE'!F17/D -> 0.042351047
C21: WACC | D21: =ke*E_perc+kd*Tax_shield*D_perc -> 0.10280515

Sheet IS - ADOBE
A1: Consolidated Statements of Income - USD ($) | B1: 12 Months Ended
A2: shares in Millions, $ in Millions | B2: Dec. 03, 2021 | C2: Dec. 02, 2022 | D2: Dec. 01, 2023 | E2: Nov. 29, 2024 | F2: Nov. 28, 2025
A3: Revenue:
A4: Revenue | B4: 15785 | C4: 17606 | D4: 19409 | E4: 21505 | F4: 23769
A5: Cost of revenue:
A6: Cost of revenue | B6: 1865 | C6: 2165 | D6: 2354 | E6: 2358 | F6: 2551
A7: Gross profit | B7: 13920 | C7: 15441 | D7: 17055 | E7: 19147 | F7: 21218
A8: Operating expenses:
A9: Research and development | B9: 2540 | C9: 2987 | D9: 3473 | E9: 3944 | F9: 4294
A10: Sales and marketing | B10: 4321 | C10: 4968 | D10: 5351 | E10: 5764 | F10: 6488
A11: General and administrative | B11: 1085 | C11: 1219 | D11: 1413 | E11: 1529 | F11: 1573
A12: Acquisition termination fee | D12: 0 | E12: 1000 | F12: 0
A13: Amortization of intangibles | B13: 172 | C13: 169 | D13: 168 | E13: 169 | F13: 157
A14: Total operating expenses | B14: 8118 | C14: 9343 | D14: 10405 | E14: 12406 | F14: 12512
A15: Operating income | B15: 5802 | C15: 6098 | D15: 6650 | E15: 6741 | F15: 8706
A16: Non-operating income (expense):
A17: Interest expense | B17: -113 | C17: -112 | D17: -113 | E17: -169 | F17: -263
A18: Investment gains (losses), net | B18: 16 | C18: -19 | D18: 16 | E18: 48 | F18: 43
A19: Other income (expense), net | B19: 0 | C19: 41 | D19: 246 | E19: 311 | F19: 248
A20: Total non-operating income (expense), net | B20: -97 | C20: -90 | D20: 149 | E20: 190 | F20: 28
A21: Income before income taxes | B21: 5705 | C21: 6008 | D21: 6799 | E21: 6931 | F21: 8734
A22: Provision for income taxes | B22: 883 | C22: 1252 | D22: 1371 | E22: 1371 | F22: 1604
A23: Net income | B23: 4822 | C23: 4756 | D23: 5428 | E23: 5560 | F23: 7130
A24: Basic net income per share (in usd per share) | B24: 10.1 | C24: 10.13 | D24: 11.87 | E24: 12.43 | F24: 16.73
A25: Shares used to compute basic net income per share (in shares) | B25: 477.3 | C25: 469.5 | D25: 457.1 | E25: 447.1 | F25: 426.2
A26: Diluted net income per share (in usd per share) | B26: 10.02 | C26: 10.1 | D26: 11.82 | E26: 12.36 | F26: 16.7
A27: Shares used to compute diluted net income per share (in shares) | B27: 481 | C27: 470.9 | D27: 459.1 | E27: 449.7 | F27: 427
A28: Subscription
A29: Revenue:
A30: Revenue | B30: 14573 | C30: 16388 | D30: 18284 | E30: 20521 | F30: 22904
A31: Cost of revenue:
A32: Cost of revenue | B32: 1374 | C32: 1646 | D32: 1822 | E32: 1799 | F32: 2027
A33: Product
A34: Revenue:
A35: Revenue | B35: 555 | C35: 532 | D35: 460 | E35: 386 | F35: 325
A36: Cost of revenue:
A37: Cost of revenue | B37: 41 | C37: 35 | D37: 29 | E37: 25 | F37: 23
A38: Services and other
A39: Revenue:
A40: Revenue | B40: 657 | C40: 686 | D40: 665 | E40: 598 | F40: 540
A41: Cost of revenue:
A42: Cost of revenue | B42: 450 | C42: 484 | D42: 503 | E42: 534 | F42: 501

Sheet BS - ADOBE
A1: Consolidated Balance Sheets - USD ($) | B1: Dec. 03, 2021 | C1: Dec. 02, 2022 | D1: Dec. 01, 2023 | E1: Nov. 29, 2024 | F1: Nov. 28, 2025
A2: $ in Millions
A3: Current assets:
A4: Cash and cash equivalents | B4: 3844 | C4: 4236 | D4: 7141 | E4: 7613 | F4: 5431
A5: Short-term investments | B5: 1954 | C5: 1860 | D5: 701 | E5: 273 | F5: 1164
A6: Trade receivables, net of allowances for doubtful accounts of $13 and of $14, respectively | B6: 1878 | C6: 2065 | D6: 2224 | E6: 2072 | F6: 2344
A7: Prepaid expenses and other current assets | B7: 993 | C7: 835 | D7: 1018 | E7: 1274 | F7: 1224
A8: Total current assets | B8: 8669 | C8: =SUM(C4:C7) -> 8996 | D8: =SUM(D4:D7) -> 11084 | E8: =SUM(E4:E7) -> 11232 | F8: =SUM(F4:F7) -> 10163
A9: Property and equipment, net | B9: 1673 | C9: 1908 | D9: 2030 | E9: 1936 | F9: 1873
A10: Operating lease right-of-use assets, net | B10: 443 | C10: 407 | D10: 358 | E10: 281 | F10: 312
A11: Goodwill | B11: 12668 | C11: 12787 | D11: 12805 | E11: 12788 | F11: 12857
A12: Other intangibles, net | B12: 1820 | C12: 1449 | D12: 1088 | E12: 782 | F12: 495
A13: Deferred income taxes | B13: 1090 | C13: 777 | D13: 1191 | E13: 1657 | F13: 2186
A14: Other assets | B14: 883 | C14: 841 | D14: 1223 | E14: 1554 | F14: 1610
A15: Total assets | B15: 27241 | C15: =SUM(C8:C14) -> 27165 | D15: =SUM(D8:D14) -> 29779 | E15: =SUM(E8:E14) -> 30230 | F15: =SUM(F8:F14) -> 29496
A16: Current liabilities:
A17: Trade payables | B17: 312 | C17: 379 | D17: 314 | E17: 361 | F17: 417
A18: Accrued expenses and other current liabilities | B18: 1736 | C18: 1790 | D18: 1942 | E18: 2336 | F18: 2648
A19: Debt | B19: 0 | C19: 500 | D19: 0 | E19: 1499 | F19: 0
A20: Deferred revenue | B20: 4733 | C20: 5297 | D20: 5837 | E20: 6131 | F20: 6905
A21: Income taxes payable | B21: 54 | C21: 75 | D21: 85 | E21: 119 | F21: 153
A22: Operating lease liabilities | B22: 97 | C22: 87 | D22: 73 | E22: 75 | F22: 77
A23: Total current liabilities | B23: 6932 | C23: =SUM(C17:C22) -> 8128 | D23: =SUM(D17:D22) -> 8251 | E23: =SUM(E17:E22) -> 10521 | F23: =SUM(F17:F22) -> 10200
A24: Long-term liabilities:
A25: Debt | B25: 4123 | C25: 3629 | D25: 3634 | E25: 4129 | F25: 6210
A26: Deferred revenue | B26: 145 | C26: 117 | D26: 113 | E26: 128 | F26: 125
A27: Income taxes payable | B27: 534 | C27: 530 | D27: 514 | E27: 548 | F27: 469
A28: Operating lease liabilities | B28: 453 | C28: 417 | D28: 373 | E28: 353 | F28: 361
A29: Other liabilities | B29: 252 | C29: 293 | D29: 376 | E29: 446 | F29: 508
A30: Total liabilities | B30: 12444 | C30: =SUM(C23:C29) -> 13114 | D30: =SUM(D23:D29) -> 13261 | E30: =SUM(E23:E29) -> 16125 | F30: =SUM(F23:F29) -> 17873
A31: Commitments and contingencies
A32: Stockholders’ equity:
A33: Preferred stock, $0.0001 par value; 2 shares authorized; none issued | B33: 0 | C33: 0 | D33: 0 | E33: 0 | F33: 0
A34: Common stock, $0.0001 par value; 900 shares authorized; 601 shares issued; 413 and 441 shares outstanding, respectively | B34: 0 | C34: 0 | D34: 0 | E34: 0 | F34: 0
A35: Additional paid-in capital | B35: 8428 | C35: 9868 | D35: 11586 | E35: 13419 | F35: 15361
A36: Retained earnings | B36: 23905 | C36: 28319 | D36: 33346 | E36: 38470 | F36: 45354
A37: Accumulated other comprehensive income (loss) | B37: -137 | C37: -293 | D37: -285 | E37: -201 | F37: -245
A38: Treasury stock, at cost (188 and 160 shares, respectively) | B38: -17399 | C38: -23843 | D38: -28129 | E38: -37583 | F38: -48847
A39: Total stockholders’ equity | B39: 14797 | C39: 14051 | D39: 16518 | E39: 14105 | F39: 11623
A40: Total liabilities and stockholders’ equity | B40: 27241 | C40: 27165 | D40: 29779 | E40: 30230 | F40: 29496

Sheet CF - ADOBE
A1: Consolidated Statements of Cash Flows - USD ($) | F1: 12 Months Ended
A2: $ in Millions | B2: Dec. 03, 2021 | C2: Dec. 02, 2022 | D2: Dec. 01, 2023 | E2: Nov. 29, 2024 | F2: Nov. 28, 2025
A3: Cash flows from operating activities:
A4: Net income | B4: 4822 | C4: 4756 | D4: 5428 | E4: 5560 | F4: 7130
A5: Adjustments to reconcile net income to net cash provided by operating activities:
A6: Depreciation, amortization and accretion | B6: 788 | C6: 856 | D6: 872 | E6: 857 | F6: 818
A7: Stock-based compensation | B7: 1069 | C7: 1440 | D7: 1718 | E7: 1833 | F7: 1942
A8: Lease-related asset impairments | B8: 73 | C8: 83 | D8: 72 | E8: 78 | F8: 0
A9: Deferred income taxes | B9: 183 | C9: 328 | D9: -426 | E9: -468 | F9: -512
A10: Unrealized losses (gains) on investments, net | B10: (4 | C10: 29 | D10: -10
A11: Other non-cash items | B11: 7 | C11: 10 | D11: 3 | E11: 52 | F11: 48
A12: Changes in operating assets and liabilities, net of acquired assets and assumed liabilities:
A13: Trade receivables, net | B13: -430 | C13: -198 | D13: -159 | E13: 143 | F13: -275
A14: Prepaid expenses and other assets | B14: -475 | C14: -94 | D14: -818 | E14: -616 | F14: -90
A15: Trade payables | B15: -20 | C15: 66 | D15: -49 | E15: 44 | F15: 64
A16: Accrued expenses and other liabilities | B16: 162 | C16: 7 | D16: 146 | E16: 196 | F16: 180
A17: Income taxes payable | B17: 2 | C17: 19 | D17: -11 | E17: 68 | F17: -45
A18: Deferred revenue | B18: 1053 | C18: 536 | D18: 536 | E18: 309 | F18: 771
A19: Net cash provided by operating activities | B19: 7230 | C19: 7838 | D19: 7302 | E19: 8056 | F19: 10031
A20: Cash flows from investing activities:
A21: Purchases of short-term investments | B21: -1533 | C21: -909 | D21: 0 | E21: -59 | F21: -2034
A22: Maturities of short-term investments | B22: 877 | C22: 683 | D22: 965 | E22: 486 | F22: 1168
A23: Proceeds from sales of short-term investments | B23: 191 | C23: 270 | D23: 223 | E23: 11 | F23: 6
A24: Acquisitions, net of cash acquired | B24: -2682 | C24: -126 | D24: 0 | E24: 0 | F24: -17
A25: Purchases of property and equipment | B25: -348 | C25: -442 | D25: -360 | E25: -183 | F25: -179
A26: Purchases of long-term investments, intangibles and other assets | B26: -42 | C26: -46 | D26: -53 | E26: -108 | F26: -134
A27: Other investing activities, net | B27: 0 | C27: 0 | D27: 1 | E27: 2 | F27: 3
A28: Net cash provided by (used for) investing activities | B28: -3537 | C28: -570 | D28: 776 | E28: 149 | F28: -1187
A29: Cash flows from financing activities:
A30: Repurchases of common stock | B30: -3950 | C30: -6550 | D30: -4400 | E30: -9500 | F30: -11281
A31: Proceeds from re-issuance of treasury stock | B31: 291 | C31: 278 | D31: 314 | E31: 361 | F31: 348
A32: Taxes paid related to net share settlement of equity awards | B32: -719 | C32: -518 | D32: -589 | E32: -677 | F32: -475
A33: Proceeds from issuance of debt | E33: 1997 | F33: 1997
A34: Repayment of debt | B34: 0 | C34: 0 | D34: -500 | E34: 0 | F34: -1500
A35: Other financing activities, net | B35: 77 | C35: -35 | D35: -7 | E35: 95 | F35: -149
A36: Net cash used for financing activities | B36: -4301 | C36: -6825 | D36: -5182 | E36: -7724 | F36: -11060
A37: Effect of foreign currency exchange rates on cash and cash equivalents | B37: -26 | C37: -51 | D37: 9 | E37: -9 | F37: 34
A38: Net change in cash and cash equivalents | B38: -634 | C38: 392 | D38: 2905 | E38: 472 | F38: -2182
A39: Cash and cash equivalents at beginning of year | B39: 4478 | C39: 3844 | D39: 4236 | E39: 7141 | F39: 7613
A40: Cash and cash equivalents at end of year | B40: 3844 | C40: 4236 | D40: 7141 | E40: 7613 | F40: 5431
A41: Supplemental disclosures:
A42: Cash paid for income taxes, net of refunds | B42: 843 | C42: 778 | D42: 1854 | E42: 1727 | F42: 2219
A43: Cash paid for interest | B43: 100 | C43: 103 | D43: 106 | E43: 143 | F43: 246

Sheet SUMMARY>>>

Sheet 52 week share price
C3: Share price
A5: • | C5: McD Valuation
C8: {=_xlfn.STOCKHISTORY("ADBE","1/1/2025","2/9/2026")} -> Date | D8: Close | F8: Valuation
C9: 45659 | D9: 441 | F9: Mean | G9: =AVERAGE(D9:D284) -> 370.3685
C10: 45660 | D10: 430.57 | F10: Median | G10: =MEDIAN(D9:D284) -> 360.97
C11: 45663 | D11: 431.18 | F11: 25th percentile | G11: =PERCENTILE(D9:D284,0.25) -> 343.355
C12: 45664 | D12: 422.63 | F12: 75th percentile | G12: =PERCENTILE(D9:D284,0.75) -> 400.035
C13: 45665 | D13: 419.58
C14: 45667 | D14: 405.92
C15: 45670 | D15: 408.5
C16: 45671 | D16: 412.71
C17: 45672 | D17: 417.28
C18: 45673 | D18: 426.93
C19: 45674 | D19: 429.99
C20: 45678 | D20: 436.36
C21: 45679 | D21: 437.32
C22: 45680 | D22: 437.28
C23: 45681 | D23: 435.38
C24: 45684 | D24: 438.6
... C284: 46062 | D284: 266.9

Sheet Summary
C3: Summary
A6: • | C6: Valuation
C8: Metrics | D8: DCF | E8: EV / Revenue | F8: EV / EBITDA | G8: P / Sales | H8: P / E | I8: 52-wk Range
C9: Mean | D9: 319 | E9: =Comps!R32 -> 196.5554 | F9: =Comps!S32 -> 742.737 | G9: =Comps!T32 -> 165.6422 | H9: =Comps!U32 -> 1101.2049 | I9: ='52 week share price'!G9 -> 370.3685
C10: Median | E10: =Comps!R33 -> 226.48275 | F10: =Comps!S33 -> 755.38949 | G10: =Comps!T33 -> 200.93309 | H10: =Comps!U33 -> 952.78606 | I10: ='52 week share price'!G10 -> 360.97 | K10: =AVERAGE(D11:D12,F11:F12,H11:I12) -> 589.70102
C11: 25th percentile | D11: 209 | E11: =Comps!R34 -> 86.225115 | F11: =Comps!S34 -> 580.32844 | G11: =Comps!T34 -> 55.200307 | H11: =Comps!U34 -> 797.66147 | I11: ='52 week share price'!G11 -> 343.355
C12: 75th percentile | D12: 443 | E12: =Comps!R35 -> 292.76776 | F12: =Comps!S35 -> 972.28679 | G12: =Comps!T35 -> 220.71046 | H12: =Comps!U35 -> 971.94145 | I12: ='52 week share price'!G12 -> 400.035
A14: • | C14: Football chart
C16: Method | D16: Min | E16: Difference | F16: Max
C17: {=TRANSPOSE(D8:I8)} -> DCF | D17: =D11 -> 209 | E17: =F17-D17 -> 234 | F17: =D12 -> 443
C18: EV / Revenue | D18: =E11 -> 86.225115 | E18: =F18-D18 -> 206.54265 | F18: =E12 -> 292.76776
C19: EV / EBITDA | D19: =F11 -> 580.32844 | E19: =F19-D19 -> 391.95835 | F19: =F12 -> 972.28679
C20: P / Sales | D20: =G11 -> 55.200307 | E20: =F20-D20 -> 165.51016 | F20: =G12 -> 220.71046
C21: P / E | D21: =H11 -> 797.66147 | E21: =F21-D21 -> 174.27998 | F21: =H12 -> 971.94145
C22: 52-wk Range | D22: =I11 -> 343.355 | E22: =F22-D22 -> 56.68 | F22: =I12 -> 400.035
A24: • | C24: End

Sheet Model Summary
C2: =[1]Model!L2 -> FY2022 | D2: =[1]Model!M2 -> FY2023 | E2: =[1]Model!N2 -> FY2024 | F2: =[1]Model!O2 -> FY2025 | G2: =[1]Model!P2 -> FY2026 | H2: =[1]Model!Q2 -> FY2027 | I2: =[1]Model!R2 -> FY2028 | J2: =[1]Model!S2 -> FY2029 | K2: =[1]Model!T2 -> FY2030
B3: Revenue | C3: =[1]Model!L4 -> 0 | D3: =[1]Model!M4 -> 0 | E3: =[1]Model!N4 -> 0 | F3: =[1]Model!O4 -> 0 | G3: =[1]Model!P4 -> 0 | H3: =[1]Model!Q4 -> 0 | I3: =[1]Model!R4 -> 0 | J3: =[1]Model!S4 -> 0 | K3: =[1]Model!T4 -> 0
B4: Growth | D4: =#REF! -> #REF! | E4: =#REF! -> #REF! | F4: =#REF! -> #REF! | G4: =#REF! -> #REF! | H4: =#REF! -> #REF! | I4: =#REF! -> #REF! | J4: =#REF! -> #REF! | K4: =#REF! -> #REF!
B6: Gross Profit | C6: =[1]Model!L6 -> 0 | D6: =[1]Model!M6 -> 0 | E6: =[1]Model!N6 -> 0 | F6: =[1]Model!O6 -> 0 | G6: =[1]Model!P6 -> 0 | H6: =[1]Model!Q6 -> 0 | I6: =[1]Model!R6 -> 0 | J6: =[1]Model!S6 -> 0 | K6: =[1]Model!T6 -> 0
B7: Margin | C7: =C6/C3 -> #DIV/0! | D7: =D6/D3 -> #DIV/0! | E7: =E6/E3 -> #DIV/0! | F7: =F6/F3 -> #DIV/0! | G7: =G6/G3 -> #DIV/0! | H7: =H6/H3 -> #DIV/0! | I7: =I6/I3 -> #DIV/0! | J7: =J6/J3 -> #DIV/0! | K7: =K6/K3 -> #DIV/0!
B9: SG&A | C9: =[1]Model!L8 -> 0 | D9: =[1]Model!M8 -> 0 | E9: =[1]Model!N8 -> 0 | F9: =[1]Model!O8 -> 0 | G9: =[1]Model!P8 -> 0 | H9: =[1]Model!Q8 -> 0 | I9: =[1]Model!R8 -> 0 | J9: =[1]Model!S8 -> 0 | K9: =[1]Model!T8 -> 0
B10: Margin | C10: =C9/C3 -> #DIV/0! | D10: =D9/D3 -> #DIV/0! | E10: =E9/E3 -> #DIV/0! | F10: =F9/F3 -> #DIV/0! | G10: =G9/G3 -> #DIV/0! | H10: =H9/H3 -> #DIV/0! | I10: =I9/I3 -> #DIV/0! | J10: =J9/J3 -> #DIV/0! | K10: =K9/K3 -> #DIV/0!
B12: EBITDA | C12: =[1]Model!L53 -> 0 | D12: =[1]Model!M53 -> 0 | E12: =[1]Model!N53 -> 0 | F12: =[1]Model!O53 -> 0 | G12: =[1]Model!P53 -> 0 | H12: =[1]Model!Q53 -> 0 | I12: =[1]Model!R53 -> 0 | J12: =[1]Model!S53 -> 0 | K12: =[1]Model!T53 -> 0
B13: Margin | C13: =C12/C3 -> #DIV/0! | D13: =D12/D3 -> #DIV/0! | E13: =E12/E3 -> #DIV/0! | F13: =F12/F3 -> #DIV/0! | G13: =G12/G3 -> #DIV/0! | H13: =H12/H3 -> #DIV/0! | I13: =I12/I3 -> #DIV/0! | J13: =J12/J3 -> #DIV/0! | K13: =K12/K3 -> #DIV/0!
B15: D&A | C15: =[1]Model!L51 -> 0 | D15: =[1]Model!M51 -> 0 | E15: =[1]Model!N51 -> 0 | F15: =[1]Model!O51 -> 0 | G15: =[1]Model!P51 -> 0 | H15: =[1]Model!Q51 -> 0 | I15: =[1]Model!R51 -> 0 | J15: =[1]Model!S51 -> 0 | K15: =[1]Model!T51 -> 0
B16: Margin | C16: =C15/C3 -> #DIV/0! | D16: =D15/D3 -> #DIV/0! | E16: =E15/E3 -> #DIV/0! | F16: =F15/F3 -> #DIV/0! | G16: =G15/G3 -> #DIV/0! | H16: =H15/H3 -> #DIV/0! | I16: =I15/I3 -> #DIV/0! | J16: =J15/J3 -> #DIV/0! | K16: =K15/K3 -> #DIV/0!
B18: Operating Income | C18: =[1]Model!L50 -> 0 | D18: =[1]Model!M50 -> 0 | E18: =[1]Model!N50 -> 0 | F18: =[1]Model!O50 -> 0 | G18: =[1]Model!P50 -> 0 | H18: =[1]Model!Q50 -> 0 | I18: =[1]Model!R50 -> 0 | J18: =[1]Model!S50 -> 0 | K18: =[1]Model!T50 -> 0
B19: Margin | C19: =C18/C3 -> #DIV/0! | D19: =D18/D3 -> #DIV/0! | E19: =E18/E3 -> #DIV/0! | F19: =F18/F3 -> #DIV/0! | G19: =G18/G3 -> #DIV/0! | H19: =H18/H3 -> #DIV/0! | I19: =I18/I3 -> #DIV/0! | J19: =J18/J3 -> #DIV/0! | K19: =K18/K3 -> #DIV/0!
B21: Interest Expense | C21: =[1]Model!L12 -> 0 | D21: =[1]Model!M12 -> 0 | E21: =[1]Model!N12 -> 0 | F21: =[1]Model!O12 -> 0 | G21: =[1]Model!P12 -> 0 | H21: =[1]Model!Q12 -> 0 | I21: =[1]Model!R12 -> 0 | J21: =[1]Model!S12 -> 0 | K21: =[1]Model!T12 -> 0
B22: EBT | C22: =[1]Model!L15 -> 0 | D22: =[1]Model!M15 -> 0 | E22: =[1]Model!N15 -> 0 | F22: =[1]Model!O15 -> 0 | G22: =[1]Model!P15 -> 0 | H22: =[1]Model!Q15 -> 0 | I22: =[1]Model!R15 -> 0 | J22: =[1]Model!S15 -> 0 | K22: =[1]Model!T15 -> 0
B24: Tax | C24: =[1]Model!L16 -> 0 | D24: =[1]Model!M16 -> 0 | E24: =[1]Model!N16 -> 0 | F24: =[1]Model!O16 -> 0 | G24: =[1]Model!P16 -> 0 | H24: =[1]Model!Q16 -> 0 | I24: =[1]Model!R16 -> 0 | J24: =[1]Model!S16 -> 0 | K24: =[1]Model!T16 -> 0
B25: Net Income | C25: =[1]Model!L18 -> 0 | D25: =[1]Model!M18 -> 0 | E25: =[1]Model!N18 -> 0 | F25: =[1]Model!O18 -> 0 | G25: =[1]Model!P18 -> 0 | H25: =[1]Model!Q18 -> 0 | I25: =[1]Model!R18 -> 0 | J25: =[1]Model!S18 -> 0 | K25: =[1]Model!T18 -> 0
B27: Sh. Out. | C27: =[1]Model!L26 -> 0 | D27: =[1]Model!M26 -> 0 | E27: =[1]Model!N26 -> 0 | F27: =[1]Model!O26 -> 0 | G27: =[1]Model!P26 -> 0 | H27: =[1]Model!Q26 -> 0 | I27: =[1]Model!R26 -> 0 | J27: =[1]Model!S26 -> 0 | K27: =[1]Model!T26 -> 0
B28: EPS | C28: =[1]Model!L22 -> 0 | D28: =[1]Model!M22 -> 0 | E28: =[1]Model!N22 -> 0 | F28: =[1]Model!O22 -> 0 | G28: =[1]Model!P22 -> 0 | H28: =[1]Model!Q22 -> 0 | I28: =[1]Model!R22 -> 0 | J28: =[1]Model!S22 -> 0 | K28: =[1]Model!T22 -> 0
B30: FCF | C30: =[1]Model!L211 -> 0 | D30: =[1]Model!M211 -> 0 | E30: =[1]Model!N211 -> 0 | F30: =[1]Model!O211 -> 0 | G30: =[1]Model!P211 -> 0 | H30: =[1]Model!Q211 -> 0 | I30: =[1]Model!R211 -> 0 | J30: =[1]Model!S211 -> 0 | K30: =[1]Model!T211 -> 0
B32: Net Leverage | C32: =[1]Model!L165 -> 0 | D32: =[1]Model!M165 -> 0 | E32: =[1]Model!N165 -> 0 | F32: =[1]Model!O165 -> 0 | G32: =[1]Model!P165 -> 0 | H32: =[1]Model!Q165 -> 0 | I32: =[1]Model!R165 -> 0 | J32: =[1]Model!S165 -> 0 | K32: =[1]Model!T165 -> 0
